nautobot_bgp_models/__init__.py
nautobot_bgp_models/api/__init__.py
nautobot_bgp_models/api/filter_backends.py
nautobot_bgp_models/api/serializers.py
nautobot_bgp_models/api/urls.py
nautobot_bgp_models/api/views.py
nautobot_bgp_models/app-config-schema.json
nautobot_bgp_models/choices.py
nautobot_bgp_models/dolt_compat.py
nautobot_bgp_models/filter_extensions.py
nautobot_bgp_models/filters.py
nautobot_bgp_models/forms.py
nautobot_bgp_models/helpers.py
nautobot_bgp_models/management/commands/generate_bgp_test_data.py
nautobot_bgp_models/migrations/0001_initial.py
nautobot_bgp_models/migrations/0002_viewsets_migration.py
nautobot_bgp_models/migrations/0003_peergroupaddressfamily_peerendpointaddressfamily.py
nautobot_bgp_models/migrations/0004_use_upstream_role_part1.py
nautobot_bgp_models/migrations/0005_use_upstream_role_part2.py
nautobot_bgp_models/migrations/0006_use_upstream_role_part3.py
nautobot_bgp_models/migrations/0007_use_upstream_role_part4.py
nautobot_bgp_models/migrations/0008_nautobotv2_updates.py
nautobot_bgp_models/migrations/0009_autonomoussystemrange.py
nautobot_bgp_models/migrations/0010_alter_autonomoussystem_status_and_more.py
nautobot_bgp_models/migrations/__init__.py
nautobot_bgp_models/models.py
nautobot_bgp_models/navigation.py
nautobot_bgp_models/signals.py
nautobot_bgp_models/static/nautobot_bgp_models/docs/404.html
nautobot_bgp_models/static/nautobot_bgp_models/docs/admin/compatibility_matrix.html
nautobot_bgp_models/static/nautobot_bgp_models/docs/admin/install.html
nautobot_bgp_models/static/nautobot_bgp_models/docs/admin/release_notes/index.html
nautobot_bgp_models/static/nautobot_bgp_models/docs/admin/release_notes/version_0.20.html
nautobot_bgp_models/static/nautobot_bgp_models/docs/admin/release_notes/version_0.7.html
nautobot_bgp_models/static/nautobot_bgp_models/docs/admin/release_notes/version_0.8.html
nautobot_bgp_models/static/nautobot_bgp_models/docs/admin/release_notes/version_0.9.html
nautobot_bgp_models-2.4.0.dist-info/LICENSE
nautobot_bgp_models-2.4.0.dist-info/METADATA
nautobot_bgp_models-2.4.0.dist-info/WHEEL
nautobot_bgp_models-2.4.0.dist-info/RECORD
