Metadata-Version: 2.3
Name: nautobot-bgp-models
Version: 2.4.0
Summary: Nautobot BGP Models App
License: Apache-2.0
Keywords: nautobot,nautobot-app,nautobot-plugin
Author: Network to Code, LLC
Author-email: opensource@networktocode.com
Requires-Python: >=3.10,<3.13
Classifier: Development Status :: 5 - Production/Stable
Classifier: Intended Audience :: Developers
Classifier: License :: OSI Approved :: Apache Software License
Classifier: Programming Language :: Python :: 3
Classifier: Programming Language :: Python :: 3.10
Classifier: Programming Language :: Python :: 3.11
Classifier: Programming Language :: Python :: 3.12
Provides-Extra: all
Requires-Dist: nautobot (>=2.4.20,<3.0.0)
Requires-Dist: netutils (>=1.6.0,<2.0.0)
Requires-Dist: toml (>=0.10.2,<0.11.0)
Project-URL: Documentation, https://docs.nautobot.com/projects/bgp-models/en/latest/
Project-URL: Homepage, https://github.com/nautobot/nautobot-app-bgp-models
Project-URL: Repository, https://github.com/nautobot/nautobot-app-bgp-models
